server.py
fastmcp_demo-0.1.1.dist-info/METADATA
fastmcp_demo-0.1.1.dist-info/WHEEL
fastmcp_demo-0.1.1.dist-info/top_level.txt
fastmcp_demo-0.1.1.dist-info/RECORD
